{
  "kind": "collectionType",
  "collectionName": "platform_articles",
  "info": {
    "singularName": "platform-article",
    "pluralName": "platform-articles",
    "displayName": "Platform Article",
    "description": "Platform-specific content (NodeVoyage, Ideonautix)"
  },
  "options": {
    "draftAndPublish": true
  },
  "pluginOptions": {
    "content-manager": {
      "visible": true
    }
  },
  "attributes": {
    "title": {
      "type": "string",
      "required": true
    },
    "slug": {
      "type": "uid",
      "targetField": "title",
      "required": true,
      "unique": true
    },
    "excerpt": {
      "type": "text"
    },
    "content": {
      "type": "richtext",
      "required": true
    },
    "featuredImage": {
      "type": "media",
      "multiple": false,
      "allowedTypes": [
        "images",
        "files",
        "videos"
      ]
    },
    "publishDate": {
      "type": "datetime",
      "required": true
    },
    "status": {
      "type": "enumeration",
      "enum": [
        "draft",
        "published"
      ],
      "default": "draft",
      "required": true
    },
    "platformType": {
      "type": "enumeration",
      "enum": [
        "NodeVoyage",
        "Ideonautix",
        "General"
      ],
      "default": "General"
    },
    "categories": {
      "type": "relation",
      "relation": "manyToMany",
      "target": "api::category.category",
      "inversedBy": "platformArticles"
    },
    "tags": {
      "type": "relation",
      "relation": "manyToMany",
      "target": "api::tag.tag",
      "inversedBy": "platformArticles"
    },
    "author": {
      "type": "relation",
      "relation": "manyToOne",
      "target": "api::author.author",
      "inversedBy": "platformArticles"
    }
  }
}
